py2Nut/__init__.py
py2Nut/_lib.py
py2Nut/nutApi.py
py2Nut/nutDataframe.py
py2Nut/nutDate.py
py2Nut/nutDb.py
py2Nut/nutEmail.py
py2Nut/nutFiles.py
py2Nut/nutFtp.py
py2Nut/nutOther.py
py2Nut/xlrd/xlsx.py
py2nut-5.2.2.dist-info/licenses/LICENSE
pynut_1tools/setup.py
pynut_1tools/pyNutTools/__init__.py
pynut_1tools/pyNutTools/_lib.py
pynut_1tools/pyNutTools/nutDataframe.py
pynut_1tools/pyNutTools/nutDate.py
pynut_1tools/pyNutTools/nutOther.py
pynut_2api/setup.py
pynut_2api/pyNutApi/__init__.py
pynut_2api/pyNutApi/_lib.py
pynut_2api/pyNutApi/nutApi.py
pynut_2files/setup.py
pynut_2files/pyNutFiles/__init__.py
pynut_2files/pyNutFiles/_lib.py
pynut_2files/pyNutFiles/nutCopy.py
pynut_2files/pyNutFiles/nutFil_old.py
pynut_2files/pyNutFiles/nutFiles.py
pynut_2files/pyNutFiles/nutXlsApp.py
pynut_2files/pyNutFiles/nutXlsFormat.py
pynut_3db/setup.py
pynut_3db/pyNutDB/__init__.py
pynut_3db/pyNutDB/_lib.py
pynut_3db/pyNutDB/nutDb.py
pynut_3email/setup.py
pynut_3email/pyNutEmail/__init__.py
pynut_3email/pyNutEmail/_lib.py
pynut_3email/pyNutEmail/nutEmail.py
pynut_3ftp/setup.py
pynut_3ftp/pyNutFtp/__init__.py
pynut_3ftp/pyNutFtp/_lib.py
pynut_3ftp/pyNutFtp/nutFtp.py
py2nut-5.2.2.dist-info/METADATA
py2nut-5.2.2.dist-info/WHEEL
py2nut-5.2.2.dist-info/top_level.txt
py2nut-5.2.2.dist-info/RECORD
