Metadata-Version: 2.4
Name: py2nut
Version: 5.2.2
Summary: This Library allows you to make Misc operations in various domain
Home-page: https://github.com/Laurent-Tupin/py2nut
Author: Laurent Tupin
Author-email: laurent.tupinn@gmail.com
License: Copyright 2022-2035
Classifier: License :: Free For Home Use
Classifier: Programming Language :: Python :: 3
Classifier: Programming Language :: Python :: 3.9
License-File: LICENSE
Requires-Dist: datefinder==0.7.3
Dynamic: author
Dynamic: author-email
Dynamic: classifier
Dynamic: description
Dynamic: description-content-type
Dynamic: home-page
Dynamic: license
Dynamic: license-file
Dynamic: requires-dist
Dynamic: summary
